Ejercicio 01/Ejercicio01.v
//Laboratorio 09 Electronica General
//Diego Esrada 19264
//Ejercicio 01

//FlipFlop Tipo D de un bit.
module FlipFlopD1(
    input wire reset, clk, enabled, I1,
    output reg O1);

    always @ (posedge clk or posedge reset) begin
        if (reset) 
            O1 <= 1'b0;
        else if (enabled)
            O1 <= I1;
        end
endmodule

//FlipFlop Tipo D de dos bits.
module FlipFlopD2(
    input wire reset, clk, enabled,
    input wire [1:0]I2,
    output wire [1:0]O2);

    FlipFlopD1 B1(clk, reset, enabled, I2[0], O2[0]);
    FlipFlopD1 B2(clk, reset, enabled, I2[1], O2[1]);
endmodule

//FlipFlop Tipo D de cuatro bits.
module FlipFlopD4(
    input wire reset, clk, enabled,
    input wire [3:0]I3,
    output wire [3:0]O3);

    FlipFlopD2 C1(clk, reset, enabled, I3[1:0], O3[1:0]);
    FlipFlopD2 C2(clk, reset, enabled, I3[3:2], O3[3:2]);
endmodule

Ejercicio 01/Ejercicio01_tb.v
//Laboratorio 09 Electronica General
//Diego Esrada 19264
//Ejercicio 01 Testbench

module testbench();
    wire O1;
    wire [1:0]O2;
    wire [3:0]O3;
    reg clk, reset, enabled, I1;
    reg [1:0]I2;
    reg [3:0]I3;

    FlipFlopD1 R1(clk, reset, enabled, I1, O1);
    FlipFlopD2 R2(clk, reset, enabled, I2, O2);
    FlipFlopD4 R3(clk, reset, enabled, I3, O3);

    initial begin
        $display("clk   reset   enable  I1  I2  I3   |   O1   O2   O3");
        $monitor("%b   %b   %b   %b   %b   %b   |   %b   %b   %b", clk, reset, enabled, I1, I2, I3, O1, O2, O3);
        clk=0; reset=0; enabled=0; I1=0; I2=2'b00; I3=4'b0000;
        #3 reset = 1;
        #3 reset = 0;
        #5 enabled = 1;
        #5 I1 = 1; I2 = 2'b01; I3 = 4'b0001;
        #5 I2 = 2'b11; I3 = 4'b0101;
        #5 I2 = 2'b10; I3 = 4'b1001;
        #5 I1 = 0;
    end

    always
        #1 clk = ~clk;

    initial 
    #35 $finish;

    initial begin
        $dumpfile("Ejercicio01_tb.vcd");
        $dumpvars(0, testbench);
    end

endmodule

Ejercicio 01/Ejercicio01_tb.vcd
$date
	Sat Oct 31 01:26:37 2020
$end
$version
	Icarus Verilog
$end
$timescale
	1ps
$end
$scope module testbench $end
$var wire 4 ! O3 [3:0] $end
$var wire 2 " O2 [1:0] $end
$var wire 1 # O1 $end
$var reg 1 $ I1 $end
$var reg 2 % I2 [1:0] $end
$var reg 4 & I3 [3:0] $end
$var reg 1 ' clk $end
$var reg 1 ( enabled $end
$var reg 1 ) reset $end
$scope module R1 $end
$var wire 1 $ I1 $end
$var wire 1 ) clk $end
$var wire 1 ( enabled $end
$var wire 1 ' reset $end
$var reg 1 # O1 $end
$upscope $end
$scope module R2 $end
$var wire 2 * I2 [1:0] $end
$var wire 1 ) clk $end
$var wire 1 ( enabled $end
$var wire 1 ' reset $end
$var wire 2 + O2 [1:0] $end
$scope module B1 $end
$var wire 1 , I1 $end
$var wire 1 ' clk $end
$var wire 1 ( enabled $end
$var wire 1 ) reset $end
$var reg 1 - O1 $end
$upscope $end
$scope module B2 $end
$var wire 1 . I1 $end
$var wire 1 ' clk $end
$var wire 1 ( enabled $end
$var wire 1 ) reset $end
$var reg 1 / O1 $end
$upscope $end
$upscope $end
$scope module R3 $end
$var wire 4 0 I3 [3:0] $end
$var wire 1 ) clk $end
$var wire 1 ( enabled $end
$var wire 1 ' reset $end
$var wire 4 1 O3 [3:0] $end
$scope module C1 $end
$var wire 2 2 I2 [1:0] $end
$var wire 1 ' clk $end
$var wire 1 ( enabled $end
$var wire 1 ) reset $end
$var wire 2 3 O2 [1:0] $end
$scope module B1 $end
$var wire 1 4 I1 $end
$var wire 1 ) clk $end
$var wire 1 ( enabled $end
$var wire 1 ' reset $end
$var reg 1 5 O1 $end
$upscope $end
$scope module B2 $end
$var wire 1 6 I1 $end
$var wire 1 ) clk $end
$var wire 1 ( enabled $end
$var wire 1 ' reset $end
$var reg 1 7 O1 $end
$upscope $end
$upscope $end
$scope module C2 $end
$var wire 2 8 I2 [1:0] $end
$var wire 1 ' clk $end
$var wire 1 ( enabled $end
$var wire 1 ) reset $end
$var wire 2 9 O2 [1:0] $end
$scope module B1 $end
$var wire 1 : I1 $end
$var wire 1 ) clk $end
$var wire 1 ( enabled $end
$var wire 1 ' reset $end
$var reg 1 ; O1 $end
$upscope $end
$scope module B2 $end
$var wire 1 < I1 $end
$var wire 1 ) clk $end
$var wire 1 ( enabled $end
$var wire 1 ' reset $end
$var reg 1 = O1 $end
$upscope $end
$upscope $end
$upscope $end
$upscope $end
$enddefinitions $end
#0
$dumpvars
x=
0<
x;
0:
bx 9
b0 8
x7
06
x5
04
bx 3
b0 2
bx 1
b0 0
x/
0.
x-
0,
bx +
b0 *
0)
0(
0'
b0 &
b0 %
0$
x#
bx "
bx !
$end
#1
0#
05
b0 3
07
0;
b0 !
b0 1
b0 9
0=
1'
#2
0'
#3
0/
b0 "
b0 +
0-
1'
1)
#4
0'
#5
1'
#6
0'
0)
#7
1'
#8
0'
#9
1'
#10
0'
#11
1'
1(
#12
0'
#13
1'
#14
0'
#15
1'
#16
14
b1 2
1,
0'
b1 &
b1 0
b1 %
b1 *
1$
#17
b1 "
b1 +
1-
1'
#18
0'
#19
1'
#20
0'
#21
b11 "
b11 +
1/
1:
b1 8
1.
1'
b101 &
b101 0
b11 %
b11 *
#22
0'
#23
1'
#24
0'
#25
1'
#26
0:
1<
b10 8
0,
0'
b1001 &
b1001 0
b10 %
b10 *
#27
b10 "
b10 +
0-
1'
#28
0'
#29
1'
#30
0'
#31
1'
0$
