Ejercicio 02/Ejercicio02.v
//Laboratorio 09 Electronica General
//Diego Esrada 19264
//Ejercicio 02

module FlipFlopD1(
    input wire clk, reset, enabled, I,
    output reg T);

    always @ (posedge clk or posedge reset) begin
        if (reset) 
            T <= 1'b0;
        else if (enabled)
            T <= I;
        end
endmodule

module FlipFlopT(
    input wire clk, reset, enabled,
    output wire T);

    FlipFlopD1 D1(clk, reset, enabled, ~T, T);

endmodule

Ejercicio 02/Ejercicio02_tb.v
    //Laboratorio 09 Electronica General
//Diego Esrada 19264
//Ejercicio 02 Testbench

module testbench();
reg clk, reset, enabled;
wire T;

FlipFlopT T01(clk, reset, enabled, T);

initial begin
    #1
    $display("clk  reset  enabled  | T");
    $monitor("%b  %b  %b  | %b", clk, reset, enabled, T);
    clk = 0; reset = 0; enabled = 0;
    #3 reset = 1;
    #3 reset = 0;
    #5 enabled = 1;
    #5 enabled = 0;
    #5 enabled = 1;

end 

always
    #1 clk = ~clk;

initial  
#30 $finish;

initial begin
    $dumpfile("Ejercicio02_tb.vcd");
    $dumpvars(0, testbench);
end

endmodule

Ejercicio 02/Ejercicio02_tb.vcd
$date
	Sat Oct 31 01:35:54 2020
$end
$version
	Icarus Verilog
$end
$timescale
	1ps
$end
$scope module testbench $end
$var wire 1 ! T $end
$var reg 1 " clk $end
$var reg 1 # enabled $end
$var reg 1 $ reset $end
$scope module T01 $end
$var wire 1 " clk $end
$var wire 1 # enabled $end
$var wire 1 $ reset $end
$var wire 1 ! T $end
$scope module D1 $end
$var wire 1 % I $end
$var wire 1 " clk $end
$var wire 1 # enabled $end
$var wire 1 $ reset $end
$var reg 1 ! T $end
$upscope $end
$upscope $end
$upscope $end
$enddefinitions $end
#0
$dumpvars
x%
x$
x#
x"
x!
$end
#1
0#
0$
1"
#2
0"
#3
1"
#4
1%
0!
0"
1$
#5
1"
#6
0"
#7
1"
0$
#8
0"
#9
1"
#10
0"
#11
1"
#12
0"
1#
#13
0%
1!
1"
#14
0"
#15
1%
0!
1"
#16
0"
#17
1"
0#
#18
0"
#19
1"
#20
0"
#21
1"
#22
0"
1#
#23
0%
1!
1"
#24
0"
#25
1%
0!
1"
#26
0"
#27
0%
1!
1"
#28
0"
#29
1%
0!
1"
