Ejercicio 04/Ejercicio04.v
//Laboratorio 09 Electronica General
//Diego Esrada 19264
// Ejercicio 04

module BufferTri(
    input wire enabled,
    input wire [3:0]inputs,
    output wire [3:0]outputs);

        assign outputs = (enabled) ? inputs:4'bz;
endmodule

Ejercicio 04/Ejercicio04_tb.v
//Laboratorio 09 Electronica General
//Diego Esrada 19264
// Ejercicio 04 Testbench

module testbench();

reg enabled;
reg [3:0]inputs;
wire [3:0]outputs;

BufferTri CON(enabled, inputs, outputs);

initial begin
    #1
    $display("enabled   inputs  | outputs");
    $monitor("%b    %b  |    %b", enabled, inputs, outputs);
    enabled = 0; inputs = 4'b0000;
    #5 enabled = 0; inputs = 4'b0101;
    #5 enabled = 1; inputs = 4'b1010;
    #5 enabled = 1; inputs = 4'b0110;
    #5 enabled = 1; inputs = 4'b1001;
    #5 enabled = 0; inputs = 4'b0111;
    #5 enabled = 1; inputs = 4'b1111;
    #5 enabled = 1; inputs = 4'b1000;
end

initial 
    #40 $finish;

initial begin
    $dumpfile("Ejercicio04_tb.vcd");
    $dumpvars(0, testbench); 
end

endmodule

Ejercicio 04/Ejercicio04_tb.vcd
$date
	Sat Oct 31 01:55:09 2020
$end
$version
	Icarus Verilog
$end
$timescale
	1ps
$end
$scope module testbench $end
$var wire 4 ! outputs [3:0] $end
$var reg 1 " enabled $end
$var reg 4 # inputs [3:0] $end
$scope module CON $end
$var wire 1 " enabled $end
$var wire 4 $ inputs [3:0] $end
$var wire 4 % outputs [3:0] $end
$upscope $end
$upscope $end
$enddefinitions $end
#0
$dumpvars
bx %
bx $
bx #
x"
bx !
$end
#1
bz !
bz %
b0 #
b0 $
0"
#6
b101 #
b101 $
#11
b1010 !
b1010 %
b1010 #
b1010 $
1"
#16
b110 !
b110 %
b110 #
b110 $
#21
b1001 !
b1001 %
b1001 #
b1001 $
#26
bz !
bz %
b111 #
b111 $
0"
#31
b1111 !
b1111 %
b1111 #
b1111 $
1"
#36
b1000 !
b1000 %
b1000 #
b1000 $
