Ejercicio 03/Ejercicio03.v
//Laboratorio 09 Electronica General
//Diego Esrada 19264
// Ejercicio 03

module FlipFlopD1(
    input wire clk, reset, enabled, I,
    output reg O);

        always @(posedge clk or posedge reset) begin
            if(reset)
                O <= 0;
            else if (enabled)
                O <= I; 
        end
endmodule

module FlipFlopJK1(
    input wire clk, reset, enabled, J, K,
    output wire O);

        wire aJ, aK, nO, nK, h;

        not(nO, O);
        not(nK, K);
        and(aJ, J, nO);
        and(aK, nK, O);
        or(h, aJ, aK);

        FlipFlopD1 JK1(clk, reset, enabled, h, O);
endmodule

Ejercicio 03/Ejercicio03_tb.v
//Laboratorio 09 Electronica General
//Diego Esrada 19264
// Ejercicio 03 Testbench

module testbench();

reg clk, reset, enabled, J, K;
wire O;

FlipFlopJK1 JK01(clk, reset, enabled, J, K, O);

initial begin
    #1
    $display("clk   reset   enabled   J   K  | O");
    $monitor("%b   %b   %b   %b   %b  | %b ", clk, reset, enabled, J, K, O);
    clk = 0; reset = 0; enabled = 0; J = 0; K = 0;
    #3 reset = 0;
    #3 reset = 1;
    #3 reset = 0;
    #5 enabled = 1; J = 1;
    #5 enabled = 0;
    #5 enabled = 1; J = 0;
    #5 K = 1;
    #5 J = 1; K = 0;
    #5 K = 1;
end

always
    #1 clk = ~clk;

initial
    #45 $finish;

initial begin
    $dumpfile("Ejercicio03_tb.vcd");
    $dumpvars(0, testbench);   
end

endmodule

Ejercicio 03/Ejercicio03_tb.vcd
$date
	Sat Oct 31 01:46:27 2020
$end
$version
	Icarus Verilog
$end
$timescale
	1ps
$end
$scope module testbench $end
$var wire 1 ! O $end
$var reg 1 " J $end
$var reg 1 # K $end
$var reg 1 $ clk $end
$var reg 1 % enabled $end
$var reg 1 & reset $end
$scope module JK01 $end
$var wire 1 " J $end
$var wire 1 # K $end
$var wire 1 ' aJ $end
$var wire 1 ( aK $end
$var wire 1 $ clk $end
$var wire 1 % enabled $end
$var wire 1 ) h $end
$var wire 1 * nK $end
$var wire 1 + nO $end
$var wire 1 & reset $end
$var wire 1 ! O $end
$scope module JK1 $end
$var wire 1 ) I $end
$var wire 1 $ clk $end
$var wire 1 % enabled $end
$var wire 1 & reset $end
$var reg 1 ! O $end
$upscope $end
$upscope $end
$upscope $end
$enddefinitions $end
#0
$dumpvars
x+
x*
x)
x(
x'
x&
x%
x$
x#
x"
x!
$end
#1
1*
0'
0#
0"
0%
0&
1$
#2
0$
#3
1$
#4
0$
#5
1$
#6
0$
#7
0)
0(
1+
0!
1$
1&
#8
0$
#9
1$
#10
0$
0&
#11
1$
#12
0$
#13
1$
#14
0$
#15
1)
1'
1$
1"
1%
#16
0$
#17
0'
1(
0+
1!
1$
#18
0$
#19
1$
#20
0$
0%
#21
1$
#22
0$
#23
1$
#24
0$
#25
1$
0"
1%
#26
0$
#27
1$
#28
0$
#29
1$
#30
0)
0(
0*
0$
1#
#31
1+
0!
1$
#32
0$
#33
1$
#34
0$
#35
1)
1*
1'
1$
0#
1"
#36
0$
#37
0'
1(
0+
1!
1$
#38
0$
#39
1$
#40
0)
0(
0*
0$
1#
#41
1)
1'
1+
0!
1$
#42
0$
#43
0)
0'
0+
1!
1$
#44
0$
#45
1)
1'
1+
0!
1$
