Ejercicio 05/Ejercicio05.v
//Laboratorio 09 Electronica General
//Diego Esrada 19264
//Ejercicio 05

module ROML(
    input wire enabled,
    input wire [6:0]I,
    output reg [12:0]O);

        always @ (enabled or I)begin
                O = 0;
            if ( enabled )
                casex (I)
                    7'bxxxxxx0: O <= 13'b1000000001000;
                    7'b00001x1: O <= 13'b0100000001000;
                    7'b00000x1: O <= 13'b1000000001000;
                    7'b00011x1: O <= 13'b1000000001000;
                    7'b00010x1: O <= 13'b1000000001000;
                    7'b0010xx1: O <= 13'b1000000001000;
                    7'b0011xx1: O <= 13'b1000000001000;
                    7'b0100xx1: O <= 13'b0011010000010;
                    7'b0101xx1: O <= 13'b0011010000100;
                    7'b0110xx1: O <= 13'b1011010100000;
                    7'b0111xx1: O <= 13'b1000000111000;
                    7'b1000x11: O <= 13'b0100000001000;
                    7'b1000x01: O <= 13'b1000000001000;
                    7'b1001x11: O <= 13'b1000000001000;
                    7'b1001x01: O <= 13'b0100000001000;
                    7'b1010xx1: O <= 13'b0011011000010;
                    7'b1011xx1: O <= 13'b1011011100000;
                    7'b1100xx1: O <= 13'b0100000001000;
                    7'b1101xx1: O <= 13'b0000000001001;
                    7'b1110xx1: O <= 13'b0011100000010;
                    7'b1111xx1: O <= 13'b1011100100000;
                endcase
        end
endmodule

Ejercicio 05/Ejercicio05_tb.v
// Marco Duarte
// TestBench
// Ejercicio 05

module testbench();

reg enabled;
reg [6:0]I;
wire [12:0]O;

ROML U01(enabled, I, O);

initial begin
    #1
    $display("Enable  Input | Output ");
    $monitor("%b       %b  |   %b   ", enabled, I, O);
    enabled = 0; I = 7'b0101010;
    #3 enabled = 1; I = 7'b0101010;
    #5 I = 7'b0000101;
    #5 I = 7'bxxxxxx0;
    #5 I = 7'b0000111;
    #5 I = 7'b0000011;
    #5 I = 7'b0001111;
    #5 I = 7'b0001011;
    #5 I = 7'b0010111;
    #5 I = 7'b0011111;
    #5 I = 7'b0100111;
    #5 I = 7'b0101111;
    #5 I = 7'b0110111;
    #5 I = 7'b0111xx1;
    #5 I = 7'b1000x11;
    #5 I = 7'b1000x01;
    #5 I = 7'b1001x11;
    #5 I = 7'b1001x01;
    #5 I = 7'b1010xx1;
    #5 I = 7'b1011xx1;
    #5 I = 7'b1100xx1;
    #5 I = 7'b1101xx1;
    #5 I = 7'b1110xx1;
    #5 enabled = 0; I = 7'b1110xx1;
    #5 enabled = 1; I = 7'b1101011;
    #5 I = 7'b1101001;
    #5 I = 7'b1001001;
    #5 I = 7'b1010001;
    #5 I = 7'b1001001;
    #5 I = 7'b0010001;
    #5 I = 7'b0000001;
    #5 I = 7'b0000100;
    #5 I = 7'b0110001;
    #5 I = 7'b0010001;

end

initial
    #160 $finish;

initial begin
    $dumpfile("Ejercicio05_tb.vcd");
    $dumpvars(0, testbench); 
end

endmodule

Ejercicio 05/Ejercicio05_tb.vcd
$date
	Sat Oct 31 00:38:20 2020
$end
$version
	Icarus Verilog
$end
$timescale
	1ps
$end
$scope module testbench $end
$var wire 13 ! O [12:0] $end
$var reg 7 " I [6:0] $end
$var reg 1 # enabled $end
$scope module U01 $end
$var wire 7 $ I [6:0] $end
$var wire 1 # enabled $end
$var reg 13 % O [12:0] $end
$upscope $end
$upscope $end
$enddefinitions $end
#0
$dumpvars
bx %
bx $
x#
bx "
bx !
$end
#1
b0 !
b0 %
b101010 "
b101010 $
0#
#4
b1000000001000 !
b1000000001000 %
1#
#9
b100000001000 !
b100000001000 %
b101 "
b101 $
#14
b1000000001000 !
b1000000001000 %
bx0 "
bx0 $
#19
b100000001000 !
b100000001000 %
b111 "
b111 $
#24
b1000000001000 !
b1000000001000 %
b11 "
b11 $
#29
b1000000001000 !
b1000000001000 %
b1111 "
b1111 $
#34
b1000000001000 !
b1000000001000 %
b1011 "
b1011 $
#39
b1000000001000 !
b1000000001000 %
b10111 "
b10111 $
#44
b1000000001000 !
b1000000001000 %
b11111 "
b11111 $
#49
b11010000010 !
b11010000010 %
b100111 "
b100111 $
#54
b11010000100 !
b11010000100 %
b101111 "
b101111 $
#59
b1011010100000 !
b1011010100000 %
b110111 "
b110111 $
#64
b1000000111000 !
b1000000111000 %
b111xx1 "
b111xx1 $
#69
b100000001000 !
b100000001000 %
b1000x11 "
b1000x11 $
#74
b1000000001000 !
b1000000001000 %
b1000x01 "
b1000x01 $
#79
b1000000001000 !
b1000000001000 %
b1001x11 "
b1001x11 $
#84
b100000001000 !
b100000001000 %
b1001x01 "
b1001x01 $
#89
b11011000010 !
b11011000010 %
b1010xx1 "
b1010xx1 $
#94
b1011011100000 !
b1011011100000 %
b1011xx1 "
b1011xx1 $
#99
b100000001000 !
b100000001000 %
b1100xx1 "
b1100xx1 $
#104
b1001 !
b1001 %
b1101xx1 "
b1101xx1 $
#109
b11100000010 !
b11100000010 %
b1110xx1 "
b1110xx1 $
#114
b0 !
b0 %
0#
#119
b1001 !
b1001 %
b1101011 "
b1101011 $
1#
#124
b1001 !
b1001 %
b1101001 "
b1101001 $
#129
b100000001000 !
b100000001000 %
b1001001 "
b1001001 $
#134
b11011000010 !
b11011000010 %
b1010001 "
b1010001 $
#139
b100000001000 !
b100000001000 %
b1001001 "
b1001001 $
#144
b1000000001000 !
b1000000001000 %
b10001 "
b10001 $
#149
b1000000001000 !
b1000000001000 %
b1 "
b1 $
#154
b1000000001000 !
b1000000001000 %
b100 "
b100 $
#159
b1011010100000 !
b1011010100000 %
b110001 "
b110001 $
